{
"meta":{"test_sets":[],"test_metrics":[],"learn_metrics":[{"best_value":"Min","name":"MultiClass"}],"launch_mode":"Train","parameters":"","iteration_count":200,"learn_sets":["learn"],"name":"experiment"},
"iterations":[
{"learn":[3.671239973],"iteration":0,"passed_time":0.1027057401,"remaining_time":20.43844229},
{"learn":[3.65142015],"iteration":1,"passed_time":0.1142451022,"remaining_time":11.31026512},
{"learn":[3.617157901],"iteration":2,"passed_time":0.1255460151,"remaining_time":8.244188327},
{"learn":[3.57181273],"iteration":3,"passed_time":0.1376272667,"remaining_time":6.743736067},
{"learn":[3.537837374],"iteration":4,"passed_time":0.1502596067,"remaining_time":5.860124662},
{"learn":[3.505390495],"iteration":5,"passed_time":0.1632770383,"remaining_time":5.279290904},
{"learn":[3.480968301],"iteration":6,"passed_time":0.1731744451,"remaining_time":4.774666843},
{"learn":[3.447636917],"iteration":7,"passed_time":0.1860701685,"remaining_time":4.465684043},
{"learn":[3.413700649],"iteration":8,"passed_time":0.1983066827,"remaining_time":4.208508487},
{"learn":[3.37957229],"iteration":9,"passed_time":0.2084065105,"remaining_time":3.959723699},
{"learn":[3.344519692],"iteration":10,"passed_time":0.2197353891,"remaining_time":3.775453504},
{"learn":[3.31897416],"iteration":11,"passed_time":0.231376775,"remaining_time":3.624902809},
{"learn":[3.271506333],"iteration":12,"passed_time":0.2440687468,"remaining_time":3.51083505},
{"learn":[3.228009805],"iteration":13,"passed_time":0.2542962311,"remaining_time":3.378507071},
{"learn":[3.191527476],"iteration":14,"passed_time":0.2657563441,"remaining_time":3.277661577},
{"learn":[3.166114892],"iteration":15,"passed_time":0.2754091557,"remaining_time":3.167205291},
{"learn":[3.123644101],"iteration":16,"passed_time":0.2861701636,"remaining_time":3.080537644},
{"learn":[3.096397675],"iteration":17,"passed_time":0.2997390988,"remaining_time":3.030695333},
{"learn":[3.068932595],"iteration":18,"passed_time":0.3110218072,"remaining_time":2.962891953},
{"learn":[3.026012879],"iteration":19,"passed_time":0.32054342,"remaining_time":2.88489078},
{"learn":[2.993718705],"iteration":20,"passed_time":0.3336996426,"remaining_time":2.844392191},
{"learn":[2.956396521],"iteration":21,"passed_time":0.3442677953,"remaining_time":2.785439435},
{"learn":[2.931394848],"iteration":22,"passed_time":0.3532485246,"remaining_time":2.718477777},
{"learn":[2.89466899],"iteration":23,"passed_time":0.3654192683,"remaining_time":2.679741301},
{"learn":[2.861730681],"iteration":24,"passed_time":0.3753644344,"remaining_time":2.627551041},
{"learn":[2.842722199],"iteration":25,"passed_time":0.3856273102,"remaining_time":2.580736615},
{"learn":[2.804347981],"iteration":26,"passed_time":0.3988594046,"remaining_time":2.555654704},
{"learn":[2.77733412],"iteration":27,"passed_time":0.4097754572,"remaining_time":2.517192094},
{"learn":[2.746785791],"iteration":28,"passed_time":0.4185256136,"remaining_time":2.467857929},
{"learn":[2.724951609],"iteration":29,"passed_time":0.4314350894,"remaining_time":2.44479884},
{"learn":[2.69299529],"iteration":30,"passed_time":0.4424985337,"remaining_time":2.412330716},
{"learn":[2.66189487],"iteration":31,"passed_time":0.4526827792,"remaining_time":2.376584591},
{"learn":[2.647325155],"iteration":32,"passed_time":0.4638296033,"remaining_time":2.347258902},
{"learn":[2.63084759],"iteration":33,"passed_time":0.4756063037,"remaining_time":2.322077836},
{"learn":[2.613864768],"iteration":34,"passed_time":0.4856615449,"remaining_time":2.289547283},
{"learn":[2.578428922],"iteration":35,"passed_time":0.4970604636,"remaining_time":2.264386557},
{"learn":[2.545442851],"iteration":36,"passed_time":0.5072614034,"remaining_time":2.234692128},
{"learn":[2.523608359],"iteration":37,"passed_time":0.5160405516,"remaining_time":2.199962352},
{"learn":[2.496221571],"iteration":38,"passed_time":0.5271369581,"remaining_time":2.176129494},
{"learn":[2.482941543],"iteration":39,"passed_time":0.5370551737,"remaining_time":2.148220695},
{"learn":[2.460237837],"iteration":40,"passed_time":0.5460726638,"remaining_time":2.117696428},
{"learn":[2.437482426],"iteration":41,"passed_time":0.5584994252,"remaining_time":2.101021647},
{"learn":[2.412263625],"iteration":42,"passed_time":0.5673427704,"remaining_time":2.071460813},
{"learn":[2.388303876],"iteration":43,"passed_time":0.5786691578,"remaining_time":2.051645196},
{"learn":[2.374958398],"iteration":44,"passed_time":0.5906641239,"remaining_time":2.03450976},
{"learn":[2.356186243],"iteration":45,"passed_time":0.5993513646,"remaining_time":2.006524134},
{"learn":[2.340235254],"iteration":46,"passed_time":0.6095608821,"remaining_time":1.984315212},
{"learn":[2.317737896],"iteration":47,"passed_time":0.6196203703,"remaining_time":1.962131173},
{"learn":[2.297316847],"iteration":48,"passed_time":0.6301887557,"remaining_time":1.942010247},
{"learn":[2.276952071],"iteration":49,"passed_time":0.6411604446,"remaining_time":1.923481334},
{"learn":[2.260948934],"iteration":50,"passed_time":0.6524515751,"remaining_time":1.906182053},
{"learn":[2.23313417],"iteration":51,"passed_time":0.6631258701,"remaining_time":1.887358246},
{"learn":[2.206704996],"iteration":52,"passed_time":0.6751087494,"remaining_time":1.872471437},
{"learn":[2.178696142],"iteration":53,"passed_time":0.6855306138,"remaining_time":1.85347166},
{"learn":[2.16596129],"iteration":54,"passed_time":0.6963265902,"remaining_time":1.835770101},
{"learn":[2.143402506],"iteration":55,"passed_time":0.7077478047,"remaining_time":1.819922926},
{"learn":[2.125510289],"iteration":56,"passed_time":0.7179842566,"remaining_time":1.801258749},
{"learn":[2.101670634],"iteration":57,"passed_time":0.7275244779,"remaining_time":1.781180618},
{"learn":[2.075358602],"iteration":58,"passed_time":0.7394564037,"remaining_time":1.767175473},
{"learn":[2.062905775],"iteration":59,"passed_time":0.7501132445,"remaining_time":1.750264237},
{"learn":[2.043146986],"iteration":60,"passed_time":0.7603360613,"remaining_time":1.732569058},
{"learn":[2.018006655],"iteration":61,"passed_time":0.774117094,"remaining_time":1.723034822},
{"learn":[2.002389684],"iteration":62,"passed_time":0.7863177117,"remaining_time":1.709928992},
{"learn":[1.985775309],"iteration":63,"passed_time":0.7982407881,"remaining_time":1.696261675},
{"learn":[1.976346576],"iteration":64,"passed_time":0.8103638069,"remaining_time":1.683063291},
{"learn":[1.961464906],"iteration":65,"passed_time":0.8224217434,"remaining_time":1.669765358},
{"learn":[1.959712636],"iteration":66,"passed_time":0.8240437048,"remaining_time":1.63578825},
{"learn":[1.947238033],"iteration":67,"passed_time":0.8340046338,"remaining_time":1.618950172},
{"learn":[1.936299351],"iteration":68,"passed_time":0.8432897085,"remaining_time":1.601028287},
{"learn":[1.926031738],"iteration":69,"passed_time":0.8551495747,"remaining_time":1.588134925},
{"learn":[1.915953592],"iteration":70,"passed_time":0.8666222981,"remaining_time":1.574567274},
{"learn":[1.892166002],"iteration":71,"passed_time":0.8769787821,"remaining_time":1.55907339},
{"learn":[1.862524738],"iteration":72,"passed_time":0.8926684929,"remaining_time":1.552998611},
{"learn":[1.848385984],"iteration":73,"passed_time":0.9054871914,"remaining_time":1.541775488},
{"learn":[1.832829927],"iteration":74,"passed_time":0.9167118768,"remaining_time":1.527853128},
{"learn":[1.823946831],"iteration":75,"passed_time":0.9259067188,"remaining_time":1.51068991},
{"learn":[1.806060418],"iteration":76,"passed_time":0.9372439383,"remaining_time":1.497155901},
{"learn":[1.795062564],"iteration":77,"passed_time":0.9454485953,"remaining_time":1.478778572},
{"learn":[1.791615214],"iteration":78,"passed_time":0.9474745642,"remaining_time":1.451195219},
{"learn":[1.782855571],"iteration":79,"passed_time":0.9566991314,"remaining_time":1.435048697},
{"learn":[1.771197474],"iteration":80,"passed_time":0.9659003513,"remaining_time":1.419038788},
{"learn":[1.760152759],"iteration":81,"passed_time":0.9754530857,"remaining_time":1.403700782},
{"learn":[1.743924793],"iteration":82,"passed_time":0.9865784074,"remaining_time":1.39071896},
{"learn":[1.736429895],"iteration":83,"passed_time":0.9961665508,"remaining_time":1.37565857},
{"learn":[1.723632699],"iteration":84,"passed_time":1.005953957,"remaining_time":1.36099653},
{"learn":[1.704422098],"iteration":85,"passed_time":1.014959185,"remaining_time":1.345411012},
{"learn":[1.694432558],"iteration":86,"passed_time":1.024695399,"remaining_time":1.330926208},
{"learn":[1.676362824],"iteration":87,"passed_time":1.036017482,"remaining_time":1.318567705},
{"learn":[1.658095538],"iteration":88,"passed_time":1.045540734,"remaining_time":1.303989005},
{"learn":[1.645906286],"iteration":89,"passed_time":1.055812982,"remaining_time":1.29043809},
{"learn":[1.6260539],"iteration":90,"passed_time":1.065830845,"remaining_time":1.276654529},
{"learn":[1.607479671],"iteration":91,"passed_time":1.07644605,"remaining_time":1.263654059},
{"learn":[1.600668723],"iteration":92,"passed_time":1.086619299,"remaining_time":1.250196398},
{"learn":[1.588143095],"iteration":93,"passed_time":1.096508971,"remaining_time":1.23648884},
{"learn":[1.579828686],"iteration":94,"passed_time":1.109029199,"remaining_time":1.225769115},
{"learn":[1.571964569],"iteration":95,"passed_time":1.119208311,"remaining_time":1.21247567},
{"learn":[1.56040633],"iteration":96,"passed_time":1.129192363,"remaining_time":1.199039314},
{"learn":[1.545837598],"iteration":97,"passed_time":1.142739283,"remaining_time":1.189381702},
{"learn":[1.53622562],"iteration":98,"passed_time":1.153872216,"remaining_time":1.177182766},
{"learn":[1.522961429],"iteration":99,"passed_time":1.164800588,"remaining_time":1.164800588},
{"learn":[1.515211519],"iteration":100,"passed_time":1.175552904,"remaining_time":1.152274629},
{"learn":[1.500205863],"iteration":101,"passed_time":1.189052462,"remaining_time":1.142422954},
{"learn":[1.492910634],"iteration":102,"passed_time":1.204392814,"remaining_time":1.134234009},
{"learn":[1.485987348],"iteration":103,"passed_time":1.218096548,"remaining_time":1.124396813},
{"learn":[1.476387003],"iteration":104,"passed_time":1.22812264,"remaining_time":1.111158579},
{"learn":[1.466174832],"iteration":105,"passed_time":1.239043736,"remaining_time":1.098774634},
{"learn":[1.457803056],"iteration":106,"passed_time":1.249520605,"remaining_time":1.086031928},
{"learn":[1.448151536],"iteration":107,"passed_time":1.258341917,"remaining_time":1.071920892},
{"learn":[1.43843848],"iteration":108,"passed_time":1.269147353,"remaining_time":1.059563387},
{"learn":[1.429910746],"iteration":109,"passed_time":1.279208651,"remaining_time":1.04662526},
{"learn":[1.414043192],"iteration":110,"passed_time":1.289361714,"remaining_time":1.033812545},
{"learn":[1.401281787],"iteration":111,"passed_time":1.30279646,"remaining_time":1.02362579},
{"learn":[1.390121934],"iteration":112,"passed_time":1.315459939,"remaining_time":1.012787741},
{"learn":[1.38071686],"iteration":113,"passed_time":1.328851582,"remaining_time":1.002466983},
{"learn":[1.36947108],"iteration":114,"passed_time":1.33920944,"remaining_time":0.9898504556},
{"learn":[1.363552372],"iteration":115,"passed_time":1.35065582,"remaining_time":0.9780611109},
{"learn":[1.353609563],"iteration":116,"passed_time":1.361390687,"remaining_time":0.9657728806},
{"learn":[1.345166565],"iteration":117,"passed_time":1.370451776,"remaining_time":0.9523478446},
{"learn":[1.33380532],"iteration":118,"passed_time":1.3817208,"remaining_time":0.940499032},
{"learn":[1.323736821],"iteration":119,"passed_time":1.391187527,"remaining_time":0.9274583511},
{"learn":[1.309021029],"iteration":120,"passed_time":1.401790405,"remaining_time":0.9152185291},
{"learn":[1.302941412],"iteration":121,"passed_time":1.413105795,"remaining_time":0.9034610818},
{"learn":[1.295180164],"iteration":122,"passed_time":1.425085099,"remaining_time":0.892126444},
{"learn":[1.286779479],"iteration":123,"passed_time":1.437240468,"remaining_time":0.8808893188},
{"learn":[1.279098956],"iteration":124,"passed_time":1.448163373,"remaining_time":0.8688980239},
{"learn":[1.268631861],"iteration":125,"passed_time":1.457987448,"remaining_time":0.8562783426},
{"learn":[1.257192505],"iteration":126,"passed_time":1.469609372,"remaining_time":0.8447360957},
{"learn":[1.250305209],"iteration":127,"passed_time":1.480491342,"remaining_time":0.8327763798},
{"learn":[1.243313902],"iteration":128,"passed_time":1.489872831,"remaining_time":0.8200075274},
{"learn":[1.232395153],"iteration":129,"passed_time":1.499784438,"remaining_time":0.8075762361},
{"learn":[1.226183184],"iteration":130,"passed_time":1.508984392,"remaining_time":0.7948085731},
{"learn":[1.218202118],"iteration":131,"passed_time":1.518727885,"remaining_time":0.7823749709},
{"learn":[1.210445805],"iteration":132,"passed_time":1.528516529,"remaining_time":0.7700045671},
{"learn":[1.199957624],"iteration":133,"passed_time":1.537383192,"remaining_time":0.7572185869},
{"learn":[1.194295044],"iteration":134,"passed_time":1.547167838,"remaining_time":0.7449326626},
{"learn":[1.186833646],"iteration":135,"passed_time":1.555942894,"remaining_time":0.7322084206},
{"learn":[1.178903947],"iteration":136,"passed_time":1.565298875,"remaining_time":0.7198089719},
{"learn":[1.172237107],"iteration":137,"passed_time":1.574698347,"remaining_time":0.7074731704},
{"learn":[1.167747556],"iteration":138,"passed_time":1.584061536,"remaining_time":0.6951636956},
{"learn":[1.160295952],"iteration":139,"passed_time":1.592982318,"remaining_time":0.6827067076},
{"learn":[1.15279684],"iteration":140,"passed_time":1.602471486,"remaining_time":0.6705377138},
{"learn":[1.139680556],"iteration":141,"passed_time":1.612936761,"remaining_time":0.658805156},
{"learn":[1.134998173],"iteration":142,"passed_time":1.62184198,"remaining_time":0.6464684815},
{"learn":[1.126033518],"iteration":143,"passed_time":1.630739335,"remaining_time":0.634176408},
{"learn":[1.120217772],"iteration":144,"passed_time":1.642596695,"remaining_time":0.6230539187},
{"learn":[1.112315876],"iteration":145,"passed_time":1.651053716,"remaining_time":0.610663703},
{"learn":[1.106275974],"iteration":146,"passed_time":1.66108487,"remaining_time":0.598894545},
{"learn":[1.09788957],"iteration":147,"passed_time":1.670709033,"remaining_time":0.5870058766},
{"learn":[1.091438418],"iteration":148,"passed_time":1.680505314,"remaining_time":0.5752065169},
{"learn":[1.08596735],"iteration":149,"passed_time":1.691341281,"remaining_time":0.5637804269},
{"learn":[1.079894263],"iteration":150,"passed_time":1.700087919,"remaining_time":0.5516841592},
{"learn":[1.071303165],"iteration":151,"passed_time":1.710338981,"remaining_time":0.5401070465},
{"learn":[1.062324758],"iteration":152,"passed_time":1.719777946,"remaining_time":0.5282978005},
{"learn":[1.056837649],"iteration":153,"passed_time":1.730527372,"remaining_time":0.5169107734},
{"learn":[1.052145972],"iteration":154,"passed_time":1.742259578,"remaining_time":0.5058172967},
{"learn":[1.04716428],"iteration":155,"passed_time":1.750988489,"remaining_time":0.4938685481},
{"learn":[1.035357734],"iteration":156,"passed_time":1.761028976,"remaining_time":0.4823200381},
{"learn":[1.030846759],"iteration":157,"passed_time":1.770369024,"remaining_time":0.470604424},
{"learn":[1.025678245],"iteration":158,"passed_time":1.779892261,"remaining_time":0.4589659289},
{"learn":[1.017197058],"iteration":159,"passed_time":1.789679083,"remaining_time":0.4474197707},
{"learn":[1.012391783],"iteration":160,"passed_time":1.798059295,"remaining_time":0.4355547361},
{"learn":[1.007542506],"iteration":161,"passed_time":1.808450572,"remaining_time":0.4242044552},
{"learn":[1.00044087],"iteration":162,"passed_time":1.817991517,"remaining_time":0.4126729211},
{"learn":[0.98907439],"iteration":163,"passed_time":1.827914535,"remaining_time":0.4012495322},
{"learn":[0.9845216065],"iteration":164,"passed_time":1.836979028,"remaining_time":0.389662218},
{"learn":[0.9799789832],"iteration":165,"passed_time":1.847409951,"remaining_time":0.3783851708},
{"learn":[0.9759032893],"iteration":166,"passed_time":1.856751791,"remaining_time":0.3669030486},
{"learn":[0.9713279186],"iteration":167,"passed_time":1.865940778,"remaining_time":0.3554172911},
{"learn":[0.9662174607],"iteration":168,"passed_time":1.875369064,"remaining_time":0.3440026094},
{"learn":[0.961383057],"iteration":169,"passed_time":1.883848262,"remaining_time":0.332443811},
{"learn":[0.9561400115],"iteration":170,"passed_time":1.893272606,"remaining_time":0.3210813192},
{"learn":[0.9513978792],"iteration":171,"passed_time":1.903103059,"remaining_time":0.3098074747},
{"learn":[0.9466666031],"iteration":172,"passed_time":1.912677436,"remaining_time":0.2985103513},
{"learn":[0.942554515],"iteration":173,"passed_time":1.923548988,"remaining_time":0.2874268602},
{"learn":[0.9363822338],"iteration":174,"passed_time":1.932697149,"remaining_time":0.2760995927},
{"learn":[0.9318422262],"iteration":175,"passed_time":1.942481183,"remaining_time":0.2648837976},
{"learn":[0.9276509017],"iteration":176,"passed_time":1.951109384,"remaining_time":0.2535339878},
{"learn":[0.9235252587],"iteration":177,"passed_time":1.961224419,"remaining_time":0.2423985237},
{"learn":[0.9112755357],"iteration":178,"passed_time":1.970505928,"remaining_time":0.2311766731},
{"learn":[0.9069629842],"iteration":179,"passed_time":1.979848589,"remaining_time":0.2199831766},
{"learn":[0.9002300687],"iteration":180,"passed_time":1.990384994,"remaining_time":0.2089354414},
{"learn":[0.8960140286],"iteration":181,"passed_time":1.998778014,"remaining_time":0.197681342},
{"learn":[0.8916000667],"iteration":182,"passed_time":2.008354267,"remaining_time":0.1865684292},
{"learn":[0.8880145204],"iteration":183,"passed_time":2.017076937,"remaining_time":0.1753979945},
{"learn":[0.8843424049],"iteration":184,"passed_time":2.026752891,"remaining_time":0.1643313155},
{"learn":[0.8765398854],"iteration":185,"passed_time":2.037045072,"remaining_time":0.1533259731},
{"learn":[0.8726920225],"iteration":186,"passed_time":2.045608837,"remaining_time":0.1422081009},
{"learn":[0.8689296969],"iteration":187,"passed_time":2.055767129,"remaining_time":0.1312191785},
{"learn":[0.8646108561],"iteration":188,"passed_time":2.065496998,"remaining_time":0.120214111},
{"learn":[0.8604562269],"iteration":189,"passed_time":2.075264592,"remaining_time":0.1092244522},
{"learn":[0.8568768051],"iteration":190,"passed_time":2.084720249,"remaining_time":0.09823289132},
{"learn":[0.8527320112],"iteration":191,"passed_time":2.094400299,"remaining_time":0.08726667912},
{"learn":[0.8492726287],"iteration":192,"passed_time":2.103259515,"remaining_time":0.07628402385},
{"learn":[0.8455744656],"iteration":193,"passed_time":2.112797485,"remaining_time":0.0653442521},
{"learn":[0.8412223188],"iteration":194,"passed_time":2.122890612,"remaining_time":0.05443309261},
{"learn":[0.8376538917],"iteration":195,"passed_time":2.134986275,"remaining_time":0.04357114847},
{"learn":[0.8304314287],"iteration":196,"passed_time":2.14461179,"remaining_time":0.0326590628},
{"learn":[0.8258322401],"iteration":197,"passed_time":2.154636937,"remaining_time":0.02176400947},
{"learn":[0.8184532913],"iteration":198,"passed_time":2.163754029,"remaining_time":0.01087313582},
{"learn":[0.8090562572],"iteration":199,"passed_time":2.172965392,"remaining_time":0}
]}